studflaw/__init__.py
studflaw/main.py
StudFlaw-0.1.1.dist-info/LICENSE.md
StudFlaw-0.1.1.dist-info/METADATA
StudFlaw-0.1.1.dist-info/WHEEL
StudFlaw-0.1.1.dist-info/entry_points.txt
StudFlaw-0.1.1.dist-info/top_level.txt
StudFlaw-0.1.1.dist-info/RECORD
